wink_sdk_lookup/__init__.py
wink_sdk_lookup/api_client.py
wink_sdk_lookup/api_response.py
wink_sdk_lookup/configuration.py
wink_sdk_lookup/exceptions.py
wink_sdk_lookup/py.typed
wink_sdk_lookup/rest.py
wink_sdk_lookup/api/__init__.py
wink_sdk_lookup/api/lookup_api.py
wink_sdk_lookup/models/__init__.py
wink_sdk_lookup/models/add_on_lightweight_non_authenticated_entity.py
wink_sdk_lookup/models/add_on_localized_inventory_non_authenticated_entity.py
wink_sdk_lookup/models/add_on_non_authenticated_entity.py
wink_sdk_lookup/models/address_non_authenticated_entity.py
wink_sdk_lookup/models/agency_score_request_non_authenticated_entity.py
wink_sdk_lookup/models/bed_non_authenticated_entity.py
wink_sdk_lookup/models/bedroom_configuration_non_authenticated_entity.py
wink_sdk_lookup/models/bedroom_non_authenticated_entity.py
wink_sdk_lookup/models/cancellation_policy_exception_non_authenticated_entity.py
wink_sdk_lookup/models/cancellation_policy_exceptions_non_authenticated_entity.py
wink_sdk_lookup/models/cancellation_policy_lightweight_non_authenticated_entity.py
wink_sdk_lookup/models/cancellation_policy_non_authenticated_entity.py
wink_sdk_lookup/models/child_non_authenticated_entity.py
wink_sdk_lookup/models/city_score_request_non_authenticated_entity.py
wink_sdk_lookup/models/city_search_request_non_authenticated_entity.py
wink_sdk_lookup/models/contact_non_authenticated_entity.py
wink_sdk_lookup/models/country_non_authenticated_entity.py
wink_sdk_lookup/models/country_score_request_non_authenticated_entity.py
wink_sdk_lookup/models/custom_monetary_amount.py
wink_sdk_lookup/models/dow_pattern_group_non_authenticated_entity.py
wink_sdk_lookup/models/extra_charge_non_authenticated_entity.py
wink_sdk_lookup/models/extra_charges_non_authenticated_entity.py
wink_sdk_lookup/models/general_manager_non_authenticated_entity.py
wink_sdk_lookup/models/generic_error_message.py
wink_sdk_lookup/models/geo_json_line_string_non_authenticated_entity.py
wink_sdk_lookup-0.0.57.dist-info/licenses/LICENSE
wink_sdk_lookup-0.0.57.dist-info/METADATA
wink_sdk_lookup-0.0.57.dist-info/WHEEL
wink_sdk_lookup-0.0.57.dist-info/top_level.txt
wink_sdk_lookup-0.0.57.dist-info/RECORD
